smartlog/__init__.py
smartlog/log.py
smartlog/mplog.py
smartlog-0.3.0.dist-info/METADATA
smartlog-0.3.0.dist-info/RECORD
smartlog-0.3.0.dist-info/WHEEL
smartlog-0.3.0.dist-info/top_level.txt
