Metadata-Version: 2.1
Name: smartlog
Version: 0.3.0
Summary: Tools to log exceptions and better interface with logging library
Home-page: https://github.com/dnut/smartlog
Author: Drew Nutter
Author-email: drew@drewnutter.com
License: GPLv3
Platform: UNKNOWN
